{"cameraMode":{"drawMode":0,"name":"Shaded","section":"Shading Mode"},"sceneLighting":true,"audioPlay":false,"sceneViewState":{"showFog":true,"showMaterialUpdate":false,"showSkybox":true,"showFlares":true,"showImageEffects":true,"showParticleSystems":true},"in2DMode":false,"pivot":{"x":0.44781631231307986,"y":0.2301183044910431,"z":0.8223336935043335},"rotation":{"x":0.14176157116889954,"y":0.4081897437572479,"z":-0.06432891637086868,"w":0.8995258212089539},"size":1.4297561645507813,"orthographic":false}